ee_client-2.4.0.dist-info/licenses/LICENSE
eeclient/__init__.py
eeclient/client.py
eeclient/data.py
eeclient/exceptions.py
eeclient/helpers.py
eeclient/models.py
eeclient/oauth_app.py
eeclient/sepal_credential_mixin.py
eeclient/tasks.py
eeclient/export/__init__.py
eeclient/export/image.py
eeclient/export/table.py
eeclient/interfaces/__init__.py
eeclient/interfaces/export.py
eeclient/interfaces/operations.py
eeclient/interfaces/tasks.py
ee_client-2.4.0.dist-info/METADATA
ee_client-2.4.0.dist-info/WHEEL
ee_client-2.4.0.dist-info/top_level.txt
ee_client-2.4.0.dist-info/RECORD
