Metadata-Version: 2.4
Name: ee-client
Version: 2.4.0
Summary: extends the capabilities of the earthengine-api by providing custom session management and client interactions
Author-email: Daniel Guerrero <dfgm2006@gmail.com>
Project-URL: Homepage, https://github.com/dfguerrerom/ee-client
Classifier: Development Status :: 3 - Alpha
Classifier: Intended Audience :: Developers
Classifier: Topic :: Software Development :: Build Tools
Classifier: License :: OSI Approved :: MIT License
Classifier: Programming Language :: Python :: 3.9
Classifier: Programming Language :: Python :: 3.10
Classifier: Programming Language :: Python :: 3.11
Requires-Python: >=3.9
License-File: LICENSE
Requires-Dist: earthengine-api
Requires-Dist: httpx[http2]
Requires-Dist: aiogoogle
Requires-Dist: tenacity
Requires-Dist: pydantic
Provides-Extra: dev
Requires-Dist: pre-commit>=2.18.0; extra == "dev"
Requires-Dist: commitizen; extra == "dev"
Requires-Dist: nox; extra == "dev"
Requires-Dist: tomli; extra == "dev"
Requires-Dist: mypy; extra == "dev"
Requires-Dist: pytest; extra == "dev"
Requires-Dist: flask; extra == "dev"
Dynamic: license-file
